Flask_Kaccel-1.0.1-nspkg.pth
Flask_Kaccel-1.0.1.dist-info/DESCRIPTION.rst
Flask_Kaccel-1.0.1.dist-info/METADATA
Flask_Kaccel-1.0.1.dist-info/RECORD
Flask_Kaccel-1.0.1.dist-info/WHEEL
Flask_Kaccel-1.0.1.dist-info/metadata.json
Flask_Kaccel-1.0.1.dist-info/namespace_packages.txt
Flask_Kaccel-1.0.1.dist-info/top_level.txt
flask_kaccel/mime.py
