Metadata-Version: 2.0
Name: Flask-Kaccel
Version: 1.0.1
Summary: Add Flask support for Nginx X-Accel
Home-page: http://bapakode.org/flask-kaccel
Author: Bapakode Open Source
Author-email: opensource@bapakode.org
License: MIT
Platform: any
Classifier: Development Status :: 4 - Beta
Classifier: Environment :: Web Environment
Classifier: Intended Audience :: Developers
Classifier: License :: OSI Approved :: MIT License
Classifier: Operating System :: OS Independent
Classifier: Programming Language :: Python
Classifier: Topic :: Internet :: WWW/HTTP :: Dynamic Content
Classifier: Topic :: Software Development :: Libraries :: Python Modules
Requires-Dist: Flask
